CurvyCUSIPs/CurveBacktester.py
CurvyCUSIPs/CurveBuilder.py
CurvyCUSIPs/CurveDataFetcher.py
CurvyCUSIPs/CurveInterpolator.py
CurvyCUSIPs/HedgeHog.py
CurvyCUSIPs/__init__.py
CurvyCUSIPs/temp.py
CurvyCUSIPs/DataFetcher/__init__.py
CurvyCUSIPs/DataFetcher/barchart.py
CurvyCUSIPs/DataFetcher/base.py
CurvyCUSIPs/DataFetcher/bbg_sef.py
CurvyCUSIPs/DataFetcher/bondsupermart.py
CurvyCUSIPs/DataFetcher/cme_sdr.py
CurvyCUSIPs/DataFetcher/dtcc.py
CurvyCUSIPs/DataFetcher/fedinvest.py
CurvyCUSIPs/DataFetcher/finra.py
CurvyCUSIPs/DataFetcher/fred.py
CurvyCUSIPs/DataFetcher/nyfrb.py
CurvyCUSIPs/DataFetcher/public_dotcom.py
CurvyCUSIPs/DataFetcher/ust.py
CurvyCUSIPs/DataFetcher/wsj.py
CurvyCUSIPs/DataFetcher/yf.py
CurvyCUSIPs/data/__init__.py
CurvyCUSIPs/models/BjorkChristensen.py
CurvyCUSIPs/models/BjorkChristensenAugmented.py
CurvyCUSIPs/models/DieboldLi.py
CurvyCUSIPs/models/MLESM.py
CurvyCUSIPs/models/MonoSpline.py
CurvyCUSIPs/models/MonotoneConvex.py
CurvyCUSIPs/models/NelsonSiegel.py
CurvyCUSIPs/models/NelsonSiegelSvensson.py
CurvyCUSIPs/models/SmithWilson.py
CurvyCUSIPs/models/Vasicek.py
CurvyCUSIPs/models/__init__.py
CurvyCUSIPs/models/calibrate.py
CurvyCUSIPs/models/nss.py
CurvyCUSIPs/utils/QL_BondPricer.py
CurvyCUSIPs/utils/RL_BondPricer.py
CurvyCUSIPs/utils/__init__.py
CurvyCUSIPs/utils/arbitragelab.py
CurvyCUSIPs/utils/pca_utils.py
CurvyCUSIPs/utils/regression_utils.py
CurvyCUSIPs/utils/rv_utils.py
CurvyCUSIPs/utils/simulation.py
CurvyCUSIPs/utils/ust_utils.py
CurvyCUSIPs/utils/ust_viz.py
CurvyCUSIPs-0.0.6.dist-info/LICENSE
CurvyCUSIPs-0.0.6.dist-info/METADATA
CurvyCUSIPs-0.0.6.dist-info/WHEEL
CurvyCUSIPs-0.0.6.dist-info/top_level.txt
CurvyCUSIPs-0.0.6.dist-info/RECORD
