Metadata-Version: 2.1
Name: CurvyCUSIPs
Version: 0.0.6
Summary: UST Research Tools
Home-page: https://github.com/yieldcurvemonkey/Curvy-CUSIPs
Author: Nonquantitative Quant
Author-email: yieldcurvemonkey@gmail.com
License: MIT
Project-URL: Source Code, https://github.com/yieldcurvemonkey/Curvy-CUSIPs
Classifier: Development Status :: 3 - Alpha
Classifier: Environment :: Console
Classifier: Environment :: Web Environment
Classifier: Intended Audience :: Developers
Classifier: Intended Audience :: Science/Research
Classifier: License :: OSI Approved :: MIT License
Classifier: Programming Language :: Python :: 3.10
Requires-Python: >=3.10
License-File: LICENSE
Requires-Dist: aiohttp>=3.10.10
Requires-Dist: httpx>=0.27.2
Requires-Dist: matplotlib>=3.9.2
Requires-Dist: numpy>=2.1.3
Requires-Dist: pandas>=2.2.3
Requires-Dist: plotly>=5.24.1
Requires-Dist: polars>=1.12.0
Requires-Dist: QuantLib>=1.36
Requires-Dist: rateslib>=1.5.0
Requires-Dist: Requests>=2.32.3
Requires-Dist: scikit-learn>=1.5.2
Requires-Dist: scipy>=1.14.1
Requires-Dist: seaborn>=0.13.2
Requires-Dist: statsmodels>=0.14.4
Requires-Dist: termcolor>=2.5.0
Requires-Dist: tqdm>=4.67.0
Requires-Dist: ujson>=5.10.0
